{
	"info": {
		"_postman_id": "4076a463-98e5-4a8b-91a5-88554c73755d",
		"name": "CNC endpoints",
		"schema": "https://schema.getpostman.com/json/collection/v2.1.0/collection.json",
		"_exporter_id": "10553870"
	},
	"item": [
		{
			"name": "Users",
			"item": [
				{
					"name": "Get all users",
					"request": {
						"method": "GET",
						"header": [],
						"url": {
							"raw": "{{baseUrl}}/users/all",
							"host": [
								"{{baseUrl}}"
							],
							"path": [
								"users",
								"all"
							]
						}
					},
					"response": []
				},
				{
					"name": "Create user",
					"request": {
						"method": "POST",
						"header": [],
						"body": {
							"mode": "raw",
							"raw": "{\r\n    \"name\": \"Test\",\r\n    \"email\": \"testing@test.com\",\r\n    \"password\": \"testing-password\",\r\n    \"role\": \"user\"\r\n}",
							"options": {
								"raw": {
									"language": "json"
								}
							}
						},
						"url": {
							"raw": "{{baseUrl}}/users",
							"host": [
								"{{baseUrl}}"
							],
							"path": [
								"users"
							]
						}
					},
					"response": []
				},
				{
					"name": "Update user",
					"request": {
						"method": "PUT",
						"header": [],
						"body": {
							"mode": "raw",
							"raw": "{\r\n    \"name\": \"Test update\",\r\n    \"email\": \"testing-update@test.com\",\r\n    \"password\": \"testing-update-password\",\r\n    \"role\": \"user\"\r\n}",
							"options": {
								"raw": {
									"language": "json"
								}
							}
						},
						"url": {
							"raw": "{{baseUrl}}/users/:user_id",
							"host": [
								"{{baseUrl}}"
							],
							"path": [
								"users",
								":user_id"
							],
							"variable": [
								{
									"key": "user_id",
									"value": "8"
								}
							]
						}
					},
					"response": []
				},
				{
					"name": "Remove user",
					"request": {
						"method": "DELETE",
						"header": [],
						"url": {
							"raw": "{{baseUrl}}/users/:user_id",
							"host": [
								"{{baseUrl}}"
							],
							"path": [
								"users",
								":user_id"
							],
							"variable": [
								{
									"key": "user_id",
									"value": "8"
								}
							]
						}
					},
					"response": []
				}
			]
		},
		{
			"name": "Files",
			"item": [
				{
					"name": "Upload file",
					"request": {
						"method": "POST",
						"header": [],
						"body": {
							"mode": "formdata",
							"formdata": [
								{
									"key": "file",
									"type": "file",
									"src": "test.gcode"
								},
								{
									"key": "user_id",
									"value": "1",
									"type": "text"
								}
							]
						},
						"url": {
							"raw": "{{baseUrl}}/files",
							"host": [
								"{{baseUrl}}"
							],
							"path": [
								"files"
							]
						}
					},
					"response": []
				},
				{
					"name": "Get all files",
					"request": {
						"method": "GET",
						"header": [],
						"url": {
							"raw": "{{baseUrl}}/files/all",
							"host": [
								"{{baseUrl}}"
							],
							"path": [
								"files",
								"all"
							]
						}
					},
					"response": []
				},
				{
					"name": "Update file name",
					"request": {
						"method": "PUT",
						"header": [],
						"body": {
							"mode": "raw",
							"raw": "{\r\n    \"user_id\": 2,\r\n    \"file_name\": \"new_name_testing.gcode\"\r\n}",
							"options": {
								"raw": {
									"language": "json"
								}
							}
						},
						"url": {
							"raw": "{{baseUrl}}/files/:file_id",
							"host": [
								"{{baseUrl}}"
							],
							"path": [
								"files",
								":file_id"
							],
							"variable": [
								{
									"key": "file_id",
									"value": "6"
								}
							]
						}
					},
					"response": []
				},
				{
					"name": "Remove file",
					"request": {
						"method": "DELETE",
						"header": [],
						"url": {
							"raw": "{{baseUrl}}/files/:file_id",
							"host": [
								"{{baseUrl}}"
							],
							"path": [
								"files",
								":file_id"
							],
							"variable": [
								{
									"key": "file_id",
									"value": "1"
								}
							]
						}
					},
					"response": []
				}
			]
		},
		{
			"name": "Tools",
			"item": [
				{
					"name": "Upload tool",
					"request": {
						"method": "POST",
						"header": [],
						"body": {
							"mode": "raw",
							"raw": "{\r\n    \"name\": \"Tool 1\",\r\n    \"description\": \"It may be useful for something\"\r\n}",
							"options": {
								"raw": {
									"language": "json"
								}
							}
						},
						"url": {
							"raw": "{{baseUrl}}/tools",
							"host": [
								"{{baseUrl}}"
							],
							"path": [
								"tools"
							]
						}
					},
					"response": []
				},
				{
					"name": "Get all tools",
					"request": {
						"method": "GET",
						"header": [],
						"url": {
							"raw": "{{baseUrl}}/tools/all",
							"host": [
								"{{baseUrl}}"
							],
							"path": [
								"tools",
								"all"
							]
						}
					},
					"response": []
				},
				{
					"name": "Update tool",
					"request": {
						"method": "PUT",
						"header": [],
						"body": {
							"mode": "raw",
							"raw": "{\r\n    \"name\": \"Tool 2\",\r\n    \"description\": \"It may also be useful for other stuff\"\r\n}",
							"options": {
								"raw": {
									"language": "json"
								}
							}
						},
						"url": {
							"raw": "{{baseUrl}}/tools/:tool_id",
							"host": [
								"{{baseUrl}}"
							],
							"path": [
								"tools",
								":tool_id"
							],
							"variable": [
								{
									"key": "tool_id",
									"value": "1"
								}
							]
						}
					},
					"response": []
				},
				{
					"name": "Remove tool",
					"request": {
						"method": "DELETE",
						"header": [],
						"url": {
							"raw": "{{baseUrl}}/tools/:tool_id",
							"host": [
								"{{baseUrl}}"
							],
							"path": [
								"tools",
								":tool_id"
							],
							"variable": [
								{
									"key": "tool_id",
									"value": "1"
								}
							]
						}
					},
					"response": []
				}
			]
		},
		{
			"name": "Materials",
			"item": [
				{
					"name": "Upload material",
					"request": {
						"method": "POST",
						"header": [],
						"body": {
							"mode": "raw",
							"raw": "{\r\n    \"name\": \"Wood\",\r\n    \"description\": \"It is some kind of wood\"\r\n}",
							"options": {
								"raw": {
									"language": "json"
								}
							}
						},
						"url": {
							"raw": "{{baseUrl}}/materials",
							"host": [
								"{{baseUrl}}"
							],
							"path": [
								"materials"
							]
						}
					},
					"response": []
				},
				{
					"name": "Get all materials",
					"request": {
						"method": "GET",
						"header": [],
						"url": {
							"raw": "{{baseUrl}}/materials/all",
							"host": [
								"{{baseUrl}}"
							],
							"path": [
								"materials",
								"all"
							]
						}
					},
					"response": []
				},
				{
					"name": "Update material",
					"request": {
						"method": "PUT",
						"header": [],
						"body": {
							"mode": "raw",
							"raw": "{\r\n    \"name\": \"Cardboard\",\r\n    \"description\": \"It is cardboard\"\r\n}",
							"options": {
								"raw": {
									"language": "json"
								}
							}
						},
						"url": {
							"raw": "{{baseUrl}}/materials/:material_id",
							"host": [
								"{{baseUrl}}"
							],
							"path": [
								"materials",
								":material_id"
							],
							"variable": [
								{
									"key": "material_id",
									"value": "1"
								}
							]
						}
					},
					"response": []
				},
				{
					"name": "Remove material",
					"request": {
						"method": "DELETE",
						"header": [],
						"url": {
							"raw": "{{baseUrl}}/materials/:material_id",
							"host": [
								"{{baseUrl}}"
							],
							"path": [
								"materials",
								":material_id"
							],
							"variable": [
								{
									"key": "material_id",
									"value": "1"
								}
							]
						}
					},
					"response": []
				}
			]
		},
		{
			"name": "Tasks",
			"item": [
				{
					"name": "Upload task",
					"request": {
						"method": "POST",
						"header": [],
						"body": {
							"mode": "raw",
							"raw": "{\r\n    \"user_id\": 1,\r\n    \"file_id\": 1,\r\n    \"tool_id\": 1,\r\n    \"material_id\": 1,\r\n    \"name\": \"My first task\",\r\n    \"note\": \"Please take into account this... and that...\"\r\n}",
							"options": {
								"raw": {
									"language": "json"
								}
							}
						},
						"url": {
							"raw": "{{baseUrl}}/tasks",
							"host": [
								"{{baseUrl}}"
							],
							"path": [
								"tasks"
							]
						}
					},
					"response": []
				},
				{
					"name": "Get all tasks",
					"request": {
						"method": "GET",
						"header": [],
						"url": {
							"raw": "{{baseUrl}}/tasks?status=pending_approval",
							"host": [
								"{{baseUrl}}"
							],
							"path": [
								"tasks"
							],
							"query": [
								{
									"key": "status",
									"value": "pending_approval",
									"description": "all, pending_approval, on_hold, in_progress, finished, rejected"
								}
							]
						}
					},
					"response": []
				},
				{
					"name": "Update task",
					"request": {
						"method": "PUT",
						"header": [],
						"body": {
							"mode": "raw",
							"raw": "{\r\n    \"user_id\": 1,\r\n    \"file_id\": 1,\r\n    \"tool_id\": 1,\r\n    \"material_id\": 1,\r\n    \"name\": \"My first task updated\",\r\n    \"priority\": 1\r\n}",
							"options": {
								"raw": {
									"language": "json"
								}
							}
						},
						"url": {
							"raw": "{{baseUrl}}/tasks/:task_id",
							"host": [
								"{{baseUrl}}"
							],
							"path": [
								"tasks",
								":task_id"
							],
							"variable": [
								{
									"key": "task_id",
									"value": "1"
								}
							]
						}
					},
					"response": []
				},
				{
					"name": "Update task status",
					"request": {
						"method": "PUT",
						"header": [],
						"body": {
							"mode": "raw",
							"raw": "{\r\n    \"user_id\": 1,\r\n    \"status\": \"on_hold\",\r\n    \"admin_id\": 1\r\n}",
							"options": {
								"raw": {
									"language": "json"
								}
							}
						},
						"url": {
							"raw": "{{baseUrl}}/tasks/:task_id/status",
							"host": [
								"{{baseUrl}}"
							],
							"path": [
								"tasks",
								":task_id",
								"status"
							],
							"variable": [
								{
									"key": "task_id",
									"value": "1"
								}
							]
						}
					},
					"response": []
				},
				{
					"name": "Cancel task",
					"request": {
						"method": "PUT",
						"header": [],
						"body": {
							"mode": "raw",
							"raw": "{\r\n    \"user_id\": 1,\r\n    \"status\": \"cancelled\",\r\n    \"admin_id\": 1,\r\n    \"cancellation_reason\": \"Because I can\"\r\n}",
							"options": {
								"raw": {
									"language": "json"
								}
							}
						},
						"url": {
							"raw": "{{baseUrl}}/tasks/:task_id/status",
							"host": [
								"{{baseUrl}}"
							],
							"path": [
								"tasks",
								":task_id",
								"status"
							],
							"variable": [
								{
									"key": "task_id",
									"value": "1"
								}
							]
						}
					},
					"response": []
				},
				{
					"name": "Remove task",
					"request": {
						"method": "DELETE",
						"header": [],
						"url": {
							"raw": "{{baseUrl}}/tasks/:task_id",
							"host": [
								"{{baseUrl}}"
							],
							"path": [
								"tasks",
								":task_id"
							],
							"variable": [
								{
									"key": "task_id",
									"value": "1"
								}
							]
						}
					},
					"response": []
				}
			]
		},
		{
			"name": "CNC",
			"item": [
				{
					"name": "Execute G-code command",
					"request": {
						"method": "POST",
						"header": [],
						"body": {
							"mode": "raw",
							"raw": "{\r\n    \"command\": \"G17 G20 G90 G94 G54\"\r\n}",
							"options": {
								"raw": {
									"language": "json"
								}
							}
						},
						"url": {
							"raw": "{{baseUrl}}/cnc/command",
							"host": [
								"{{baseUrl}}"
							],
							"path": [
								"cnc",
								"command"
							]
						}
					},
					"response": []
				}
			]
		}
	]
}
